<localization>
<set id="name-campstructure-gradarbeacon">
		<string lang="de">Gradar Leuchtfeuer</string>
		<string lang="en">Gradar Beacon</string>
		<string lang="fr">Phare Gradar</string>
		<string lang="zh">格拉达灯塔</string>
		<string lang="jp">信号塔</string>
		<string lang="ru">Грэдар-маяк</string>
		<string lang="es">Baliza Gradar</string>
		<string lang="kr">중력파 송신소</string>
		<string lang="pt-br">Baliza Gradar</string>
		<string lang="zh-tw">格拉達燈塔</string>
		<string lang="uk">Градарський Маяк</string>
</set>
<set id="description-campstructure-gradarbeacon">
	<string lang="en">Get an additional module as an option for loot</string>
		<string lang="uk">Отримайте додатковий модуль як опцію для здобичі</string>
</set>
<set id="quote-campstructure-gradarbeacon">
	<string lang="de">Unsere einzige Möglichkeit, andere Überlebende zu kontaktieren</string>
	<string lang="en">“Our only means to contact other survivors”</string>
	<string lang="fr">Notre seul moyen de contacter d'autres survivants</string>
	<string lang="zh">我们联系其他幸存者的唯一途径</string>
	<string lang="jp">他の生存者との唯一の連絡手段</string>
	<string lang="ru">Наш единственный способ связаться с другими выжившими</string>
	<string lang="es">Nuestro único medio para contactar con otros supervivientes</string>
	<string lang="kr">다른 생존자들과 접촉할 유일한 수단</string>
	<string lang="pt-br">Nosso único meio de entrar em contato com outros sobreviventes</string>
		<string lang="uk">«Наш єдиний спосіб зв’язатися з іншими вцілілими»</string>
</set>
<set id="name-campstructure-silo">
		<string lang="de">Silo</string>
		<string lang="en">Silo</string>
		<string lang="fr">Silo</string>
		<string lang="zh">仓库</string>
		<string lang="jp">シロ</string>
		<string lang="ru">Силос</string>
		<string lang="es">Silo</string>
		<string lang="kr">사일로</string>
		<string lang="pt-br">Silo</string>
		<string lang="uk">Сило</string>
</set>
</localization>